Workbook

Sheet Модель
A1: White.Lev.Travel · «Білий Лев» — фінансова модель комплексу «Варуш»
A2: Прикарпаття / Турківщина · Сценарій A: 2×Compact + Comfort + VIP · редагуй ЖОВТІ комірки
A4: ГЛОБАЛЬНІ ПРИПУЩЕННЯ
A5: Курс, грн за $ | B5: 42
A6: Завантаження, % року | B6: 0.45
A7: Опекс + управління, % валового доходу | B7: 0.45
A8: Маржа девелопера, % | B8: 0.3
A9: Спільна інженерія на комплекс, $ | B9: 75000 | C9: ← розподіляється порівну між будинками (спрощення)
A10: Будинків усього (авто, для розподілу інж.) | B10: =SUM(B18:D18) -> 4
A12: ЕКОНОМІКА ПО ТИПАХ БУДИНКІВ
A13: Показник | B13: Compact | C13: Comfort | D13: VIP-вілла
A14: Площа, м² | B14: 40 | C14: 55 | D14: 90
A15: Собівартість будівництва, $/м² | B15: 850 | C15: 1000 | D15: 1300
A16: Меблі + wellness + тераса, $ (VIP: джакузі; кошторис уточнити) | B16: 12000 | C16: 18000 | D16: 40000
A17: Ставка оренди, $/ніч | B17: 76 | C17: 100 | D17: 167
A18: Кількість будинків, шт | B18: 2 | C18: 1 | D18: 1
A19: Будівництво, $ | B19: =B14*B15 -> 34000 | C19: =C14*C15 -> 55000 | D19: =D14*D15 -> 117000
A20: All-in собівартість (без інж.), $ | B20: =B19+B16 -> 46000 | C20: =C19+C16 -> 73000 | D20: =D19+D16 -> 157000
A21: Частка спільної інженерії, $ | B21: =$B$9/$B$10 -> 18750 | C21: =$B$9/$B$10 -> 18750 | D21: =$B$9/$B$10 -> 18750
A22: Повна собівартість / будинок, $ | B22: =B20+B21 -> 64750 | C22: =C20+C21 -> 91750 | D22: =D20+D21 -> 175750
A23: Ціна продажу інвестору, $ | B23: =B22*(1+$B$8) -> 84175 | C23: =C22*(1+$B$8) -> 119275 | D23: =D22*(1+$B$8) -> 228475
A24: Валовий дохід оренди / рік, $ | B24: =B17*365*$B$6 -> 12483 | C24: =C17*365*$B$6 -> 16425 | D24: =D17*365*$B$6 -> 27429.75
A25: Чистий дохід інвестору / рік, $ | B25: =B24*(1-$B$7) -> 6865.65 | C25: =C24*(1-$B$7) -> 9033.75 | D25: =D24*(1-$B$7) -> 15086.362
A26: Дохідність інвестора, % | B26: =B25/B23 -> 0.081564004 | C26: =C25/C23 -> 0.075738839 | D26: =D25/D23 -> 0.066030693
A27: Окупність, років | B27: =B23/B25 -> 12.26031 | C27: =C23/C25 -> 13.203266 | D27: =D23/D25 -> 15.144472
A28: Маржа девелопера / будинок, $ | B28: =B23-B22 -> 19425 | C28: =C23-C22 -> 27525 | D28: =D23-D22 -> 52725
A30: ПІДСУМОК КОМПЛЕКСУ (Сценарій A)
A31: Повний капекс комплексу, $ | B31: =SUMPRODUCT(B22:D22,B18:D18) -> 397000
A32: Виручка від продажу всіх будинків, $ | B32: =SUMPRODUCT(B23:D23,B18:D18) -> 516100
A33: Маржа девелопера всього, $ | B33: =B32-B31 -> 119100
A34: Маржа девелопера, % до капексу | B34: =B33/B31 -> 0.3
A35: Якщо лишити собі: чистий дохід/рік усіх, $ | B35: =SUMPRODUCT(B25:D25,B18:D18) -> 37851.412
A37: Легенда:
A38: Жовті комірки (синій текст) — редаговані припущення. Чорні — формули, перераховуються автоматично.
A39: Ставки й собівартість — ГІПОТЕЗА за ринком 2026 (див. 04_market_monitor.md). Локація тиха → консервативне завантаження 45%.

Sheet Чутливість
A1: Чутливість дохідності інвестора — по типах
A2: Рядки — завантаження; стовпці — ставка $/ніч. Комірка = дохідність до ціни продажу типу. Опекс+управління береться з «Модель».
A4: Compact | D4: Ціна продажу, $ | E4: =Модель!B23 -> 84175
A5: Завантаж. \ $/ніч | B5: 55 | C5: 70 | D5: 85 | E5: 100
A6: 0.35 | B6: =(B$5*365*$A6*(1-Модель!$B$7))/$E$4 -> 0.045909563 | C6: =(C$5*365*$A6*(1-Модель!$B$7))/$E$4 -> 0.058430353 | D6: =(D$5*365*$A6*(1-Модель!$B$7))/$E$4 -> 0.070951143 | E6: =(E$5*365*$A6*(1-Модель!$B$7))/$E$4 -> 0.083471933
A7: 0.45 | B7: =(B$5*365*$A7*(1-Модель!$B$7))/$E$4 -> 0.059026582 | C7: =(C$5*365*$A7*(1-Модель!$B$7))/$E$4 -> 0.07512474 | D7: =(D$5*365*$A7*(1-Модель!$B$7))/$E$4 -> 0.091222899 | E7: =(E$5*365*$A7*(1-Модель!$B$7))/$E$4 -> 0.10732106
A8: 0.55 | B8: =(B$5*365*$A8*(1-Модель!$B$7))/$E$4 -> 0.0721436 | C8: =(C$5*365*$A8*(1-Модель!$B$7))/$E$4 -> 0.091819127 | D8: =(D$5*365*$A8*(1-Модель!$B$7))/$E$4 -> 0.11149465 | E8: =(E$5*365*$A8*(1-Модель!$B$7))/$E$4 -> 0.13117018
A11: Comfort | D11: Ціна продажу, $ | E11: =Модель!C23 -> 119275
A12: Завантаж. \ $/ніч | B12: 80 | C12: 95 | D12: 110 | E12: 125
A13: 0.35 | B13: =(B$12*365*$A13*(1-Модель!$B$7))/$E$11 -> 0.047126389 | C13: =(C$12*365*$A13*(1-Модель!$B$7))/$E$11 -> 0.055962586 | D13: =(D$12*365*$A13*(1-Модель!$B$7))/$E$11 -> 0.064798784 | E13: =(E$12*365*$A13*(1-Модель!$B$7))/$E$11 -> 0.073634982
A14: 0.45 | B14: =(B$12*365*$A14*(1-Модель!$B$7))/$E$11 -> 0.060591071 | C14: =(C$12*365*$A14*(1-Модель!$B$7))/$E$11 -> 0.071951897 | D14: =(D$12*365*$A14*(1-Модель!$B$7))/$E$11 -> 0.083312723 | E14: =(E$12*365*$A14*(1-Модель!$B$7))/$E$11 -> 0.094673549
A15: 0.55 | B15: =(B$12*365*$A15*(1-Модель!$B$7))/$E$11 -> 0.074055754 | C15: =(C$12*365*$A15*(1-Модель!$B$7))/$E$11 -> 0.087941207 | D15: =(D$12*365*$A15*(1-Модель!$B$7))/$E$11 -> 0.10182666 | E15: =(E$12*365*$A15*(1-Модель!$B$7))/$E$11 -> 0.11571211
A18: VIP-вілла | D18: Ціна продажу, $ | E18: =Модель!D23 -> 228475
A19: Завантаж. \ $/ніч | B19: 150 | C19: 175 | D19: 200 | E19: 230
A20: 0.35 | B20: =(B$19*365*$A20*(1-Модель!$B$7))/$E$18 -> 0.046129226 | C20: =(C$19*365*$A20*(1-Модель!$B$7))/$E$18 -> 0.053817431 | D20: =(D$19*365*$A20*(1-Модель!$B$7))/$E$18 -> 0.061505635 | E20: =(E$19*365*$A20*(1-Модель!$B$7))/$E$18 -> 0.07073148
A21: 0.45 | B21: =(B$19*365*$A21*(1-Модель!$B$7))/$E$18 -> 0.059309005 | C21: =(C$19*365*$A21*(1-Модель!$B$7))/$E$18 -> 0.06919384 | D21: =(D$19*365*$A21*(1-Модель!$B$7))/$E$18 -> 0.079078674 | E21: =(E$19*365*$A21*(1-Модель!$B$7))/$E$18 -> 0.090940475
A22: 0.55 | B22: =(B$19*365*$A22*(1-Модель!$B$7))/$E$18 -> 0.072488784 | C22: =(C$19*365*$A22*(1-Модель!$B$7))/$E$18 -> 0.084570248 | D22: =(D$19*365*$A22*(1-Модель!$B$7))/$E$18 -> 0.096651712 | E22: =(E$19*365*$A22*(1-Модель!$B$7))/$E$18 -> 0.11114947
A26: Базовий сценарій моделі: завантаження 45%, ставки Compact $76 / Comfort $100 / VIP $167.

Sheet Сукупний дохід
A1: White.Lev.Travel — сукупний дохід інвестора (оренда + приріст вартості)
A2: Головна теза: оренда тримає актив, а основний виграш — у ПРИРОСТІ вартості (близькість до кордону з Польщею, повоєнне відновлення). Редагуй жовті комірки.
A4: ПРИПУЩЕННЯ (редаговані)
A5: Період утримання, років | B5: 5
A6: Приріст вартості /рік — Обережний | B6: 0.03
A7: Приріст вартості /рік — Базовий | B7: 0.07
A8: Приріст вартості /рік — Проривний (повоєнний) | B8: 0.12 | C8: ← близькість кордону + релокації + відновлення
A10: Тип · сценарій | B10: Ціна активу, $ | C10: Приріст %/рік | D10: Вартість через N р., $ | E10: Кап. приріст, $ | F10: Оренда (чиста) за N р., $ | G10: Сукупний дохід, $ | H10: Сукупно, % до ціни | I10: Серед. річна, %
A11: Compact · Обережний | B11: =Модель!B23 -> 84175 | C11: =$B$6 -> 0.03 | D11: =B11*(1+C11)^$B$5 -> 97581.895 | E11: =D11-B11 -> 13406.895 | F11: =Модель!B25*$B$5 -> 34328.25 | G11: =E11+F11 -> 47735.145 | H11: =G11/B11 -> 0.56709409 | I11: =H11/$B$5 -> 0.11341882
A12: Compact · Базовий | B12: =Модель!B23 -> 84175 | C12: =$B$7 -> 0.07 | D12: =B12*(1+C12)^$B$5 -> 118059.79 | E12: =D12-B12 -> 33884.792 | F12: =Модель!B25*$B$5 -> 34328.25 | G12: =E12+F12 -> 68213.042 | H12: =G12/B12 -> 0.81037175 | I12: =H12/$B$5 -> 0.16207435
A13: Compact · Проривний | B13: =Модель!B23 -> 84175 | C13: =$B$8 -> 0.12 | D13: =B13*(1+C13)^$B$5 -> 148345.11 | E13: =D13-B13 -> 64170.111 | F13: =Модель!B25*$B$5 -> 34328.25 | G13: =E13+F13 -> 98498.361 | H13: =G13/B13 -> 1.1701617 | I13: =H13/$B$5 -> 0.23403234
A14: Comfort · Обережний | B14: =Модель!C23 -> 119275 | C14: =$B$6 -> 0.03 | D14: =B14*(1+C14)^$B$5 -> 138272.42 | E14: =D14-B14 -> 18997.415 | F14: =Модель!C25*$B$5 -> 45168.75 | G14: =E14+F14 -> 64166.165 | H14: =G14/B14 -> 0.53796827 | I14: =H14/$B$5 -> 0.10759365
A15: Comfort · Базовий | B15: =Модель!C23 -> 119275 | C15: =$B$7 -> 0.07 | D15: =B15*(1+C15)^$B$5 -> 167289.36 | E15: =D15-B15 -> 48014.358 | F15: =Модель!C25*$B$5 -> 45168.75 | G15: =E15+F15 -> 93183.108 | H15: =G15/B15 -> 0.78124592 | I15: =H15/$B$5 -> 0.15624918
A16: Comfort · Проривний | B16: =Модель!C23 -> 119275 | C16: =$B$8 -> 0.12 | D16: =B16*(1+C16)^$B$5 -> 210203.3 | E16: =D16-B16 -> 90928.304 | F16: =Модель!C25*$B$5 -> 45168.75 | G16: =E16+F16 -> 136097.05 | H16: =G16/B16 -> 1.1410359 | I16: =H16/$B$5 -> 0.22820718
A17: VIP-вілла · Обережний | B17: =Модель!D23 -> 228475 | C17: =$B$6 -> 0.03 | D17: =B17*(1+C17)^$B$5 -> 264865.14 | E17: =D17-B17 -> 36390.144 | F17: =Модель!D25*$B$5 -> 75431.812 | G17: =E17+F17 -> 111821.96 | H17: =G17/B17 -> 0.48942754 | I17: =H17/$B$5 -> 0.097885507
A18: VIP-вілла · Базовий | B18: =Модель!D23 -> 228475 | C18: =$B$7 -> 0.07 | D18: =B18*(1+C18)^$B$5 -> 320448.01 | E18: =D18-B18 -> 91973.007 | F18: =Модель!D25*$B$5 -> 75431.812 | G18: =E18+F18 -> 167404.82 | H18: =G18/B18 -> 0.73270519 | I18: =H18/$B$5 -> 0.14654104
A19: VIP-вілла · Проривний | B19: =Модель!D23 -> 228475 | C19: =$B$8 -> 0.12 | D19: =B19*(1+C19)^$B$5 -> 402651.02 | E19: =D19-B19 -> 174176.02 | F19: =Модель!D25*$B$5 -> 75431.812 | G19: =E19+F19 -> 249607.83 | H19: =G19/B19 -> 1.0924951 | I19: =H19/$B$5 -> 0.21849903
A21: Оренду взято незмінною (консервативно, без індексації). Приріст вартості — складний відсоток.
A22: ⚠️ Приріст вартості — СПЕКУЛЯТИВНА теза, не гарантія: залежить від строків завершення війни, темпів відновлення та ринку. Оренда — реальний поточний дохід, що тримає актив.
A23: Сукупний дохід = капітальний приріст активу + накопичена чиста оренда за період утримання.
